{"__type__":"cc.JsonAsset","_name":"grow-gold","json":[{"id":1,"realGoldParam":0,"realOfflineParam":0,"showTips":6,"price":169},{"id":2,"realGoldParam":50,"realOfflineParam":50,"showTips":9,"price":353},{"id":3,"realGoldParam":100,"realOfflineParam":100,"showTips":12,"price":529},{"id":4,"realGoldParam":150,"realOfflineParam":150,"showTips":15,"price":719},{"id":5,"realGoldParam":200,"realOfflineParam":200,"showTips":18,"price":937},{"id":6,"realGoldParam":250,"realOfflineParam":250,"showTips":21,"price":1081},{"id":7,"realGoldParam":300,"realOfflineParam":300,"showTips":24,"price":1297},{"id":8,"realGoldParam":350,"realOfflineParam":350,"showTips":27,"price":1514},{"id":9,"realGoldParam":400,"realOfflineParam":400,"showTips":30,"price":1730},{"id":10,"realGoldParam":450,"realOfflineParam":450,"showTips":33,"price":3892},{"id":11,"realGoldParam":500,"realOfflineParam":500,"showTips":36,"price":4324},{"id":12,"realGoldParam":550,"realOfflineParam":550,"showTips":39,"price":4829},{"id":13,"realGoldParam":600,"realOfflineParam":600,"showTips":42,"price":5333},{"id":14,"realGoldParam":650,"realOfflineParam":650,"showTips":45,"price":5694},{"id":15,"realGoldParam":700,"realOfflineParam":700,"showTips":48,"price":6198},{"id":16,"realGoldParam":750,"realOfflineParam":750,"showTips":51,"price":6775},{"id":17,"realGoldParam":800,"realOfflineParam":800,"showTips":54,"price":7279},{"id":18,"realGoldParam":850,"realOfflineParam":850,"showTips":57,"price":7856},{"id":19,"realGoldParam":900,"realOfflineParam":900,"showTips":60,"price":8288},{"id":20,"realGoldParam":950,"realOfflineParam":950,"showTips":63,"price":8865},{"id":21,"realGoldParam":1000,"realOfflineParam":1000,"showTips":66,"price":9441},{"id":22,"realGoldParam":1050,"realOfflineParam":1050,"showTips":69,"price":10018},{"id":23,"realGoldParam":1100,"realOfflineParam":1100,"showTips":72,"price":10523},{"id":24,"realGoldParam":1150,"realOfflineParam":1150,"showTips":75,"price":11099},{"id":25,"realGoldParam":1200,"realOfflineParam":1200,"showTips":78,"price":11748},{"id":26,"realGoldParam":1250,"realOfflineParam":1250,"showTips":81,"price":12396},{"id":27,"realGoldParam":1300,"realOfflineParam":1300,"showTips":84,"price":13045},{"id":28,"realGoldParam":1350,"realOfflineParam":1350,"showTips":87,"price":13550},{"id":29,"realGoldParam":1400,"realOfflineParam":1400,"showTips":90,"price":14270},{"id":30,"realGoldParam":1450,"realOfflineParam":1450,"showTips":93,"price":22414},{"id":31,"realGoldParam":1500,"realOfflineParam":1500,"showTips":96,"price":23495},{"id":32,"realGoldParam":1550,"realOfflineParam":1550,"showTips":99,"price":24216},{"id":33,"realGoldParam":1600,"realOfflineParam":1600,"showTips":102,"price":25369},{"id":34,"realGoldParam":1650,"realOfflineParam":1650,"showTips":105,"price":26450},{"id":35,"realGoldParam":1700,"realOfflineParam":1700,"showTips":108,"price":27604},{"id":36,"realGoldParam":1750,"realOfflineParam":1750,"showTips":111,"price":28396},{"id":37,"realGoldParam":1800,"realOfflineParam":1800,"showTips":114,"price":29550},{"id":38,"realGoldParam":1850,"realOfflineParam":1850,"showTips":117,"price":30775},{"id":39,"realGoldParam":1900,"realOfflineParam":1900,"showTips":120,"price":32000},{"id":40,"realGoldParam":1950,"realOfflineParam":1950,"showTips":123,"price":44252},{"id":41,"realGoldParam":2000,"realOfflineParam":2000,"showTips":126,"price":45405},{"id":42,"realGoldParam":2050,"realOfflineParam":2050,"showTips":129,"price":47640},{"id":43,"realGoldParam":2100,"realOfflineParam":2100,"showTips":132,"price":50018},{"id":44,"realGoldParam":2150,"realOfflineParam":2150,"showTips":135,"price":52973},{"id":45,"realGoldParam":2200,"realOfflineParam":2200,"showTips":138,"price":55423},{"id":46,"realGoldParam":2250,"realOfflineParam":2250,"showTips":141,"price":58595},{"id":47,"realGoldParam":2300,"realOfflineParam":2300,"showTips":144,"price":61117},{"id":48,"realGoldParam":2350,"realOfflineParam":2350,"showTips":147,"price":64432},{"id":49,"realGoldParam":2400,"realOfflineParam":2400,"showTips":150,"price":67820},{"id":50,"realGoldParam":2450,"realOfflineParam":2450,"showTips":153,"price":89946},{"id":51,"realGoldParam":2500,"realOfflineParam":2500,"showTips":156,"price":94414},{"id":52,"realGoldParam":2550,"realOfflineParam":2550,"showTips":159,"price":98955},{"id":53,"realGoldParam":2600,"realOfflineParam":2600,"showTips":162,"price":104505},{"id":54,"realGoldParam":2650,"realOfflineParam":2650,"showTips":165,"price":110198},{"id":55,"realGoldParam":2700,"realOfflineParam":2700,"showTips":168,"price":116036},{"id":56,"realGoldParam":2750,"realOfflineParam":2750,"showTips":171,"price":120144},{"id":57,"realGoldParam":2800,"realOfflineParam":2800,"showTips":174,"price":125189},{"id":58,"realGoldParam":2850,"realOfflineParam":2850,"showTips":177,"price":130450},{"id":59,"realGoldParam":2900,"realOfflineParam":2900,"showTips":180,"price":135712},{"id":60,"realGoldParam":2950,"realOfflineParam":2950,"showTips":183,"price":169369},{"id":61,"realGoldParam":3000,"realOfflineParam":3000,"showTips":186,"price":177297},{"id":62,"realGoldParam":3050,"realOfflineParam":3050,"showTips":189,"price":184000},{"id":63,"realGoldParam":3100,"realOfflineParam":3100,"showTips":192,"price":192216},{"id":64,"realGoldParam":3150,"realOfflineParam":3150,"showTips":195,"price":199279},{"id":65,"realGoldParam":3200,"realOfflineParam":3200,"showTips":198,"price":207784},{"id":66,"realGoldParam":3250,"realOfflineParam":3250,"showTips":201,"price":216432},{"id":67,"realGoldParam":3300,"realOfflineParam":3300,"showTips":204,"price":225297},{"id":68,"realGoldParam":3350,"realOfflineParam":3350,"showTips":207,"price":306739},{"id":69,"realGoldParam":3400,"realOfflineParam":3400,"showTips":210,"price":315099},{"id":70,"realGoldParam":3450,"realOfflineParam":3450,"showTips":213,"price":375207},{"id":71,"realGoldParam":3500,"realOfflineParam":3500,"showTips":216,"price":382847},{"id":72,"realGoldParam":3550,"realOfflineParam":3550,"showTips":219,"price":390559},{"id":73,"realGoldParam":3600,"realOfflineParam":3600,"showTips":222,"price":400721},{"id":74,"realGoldParam":3650,"realOfflineParam":3650,"showTips":225,"price":408577},{"id":75,"realGoldParam":3700,"realOfflineParam":3700,"showTips":228,"price":416505},{"id":76,"realGoldParam":3750,"realOfflineParam":3750,"showTips":231,"price":424505},{"id":77,"realGoldParam":3800,"realOfflineParam":3800,"showTips":234,"price":435099},{"id":78,"realGoldParam":3850,"realOfflineParam":3850,"showTips":237,"price":443243},{"id":79,"realGoldParam":3900,"realOfflineParam":3900,"showTips":240,"price":451459},{"id":80,"realGoldParam":3950,"realOfflineParam":3950,"showTips":243,"price":525477},{"id":81,"realGoldParam":4000,"realOfflineParam":4000,"showTips":246,"price":538018},{"id":82,"realGoldParam":4050,"realOfflineParam":4050,"showTips":249,"price":547676},{"id":83,"realGoldParam":4100,"realOfflineParam":4100,"showTips":252,"price":557405},{"id":84,"realGoldParam":4150,"realOfflineParam":4150,"showTips":255,"price":567207},{"id":85,"realGoldParam":4200,"realOfflineParam":4200,"showTips":258,"price":580252},{"id":86,"realGoldParam":4250,"realOfflineParam":4250,"showTips":261,"price":590270},{"id":87,"realGoldParam":4300,"realOfflineParam":4300,"showTips":264,"price":600360},{"id":88,"realGoldParam":4350,"realOfflineParam":4350,"showTips":267,"price":610523},{"id":89,"realGoldParam":4400,"realOfflineParam":4400,"showTips":270,"price":624000},{"id":90,"realGoldParam":4450,"realOfflineParam":4450,"showTips":273,"price":713586},{"id":91,"realGoldParam":4500,"realOfflineParam":4500,"showTips":276,"price":734993},{"id":92,"realGoldParam":4550,"realOfflineParam":4550,"showTips":279,"price":757043},{"id":93,"realGoldParam":4600,"realOfflineParam":4600,"showTips":282,"price":779754},{"id":94,"realGoldParam":4650,"realOfflineParam":4650,"showTips":285,"price":803147},{"id":95,"realGoldParam":4700,"realOfflineParam":4700,"showTips":288,"price":827241},{"id":96,"realGoldParam":4750,"realOfflineParam":4750,"showTips":291,"price":852059},{"id":97,"realGoldParam":4800,"realOfflineParam":4800,"showTips":294,"price":877620},{"id":98,"realGoldParam":4850,"realOfflineParam":4850,"showTips":297,"price":903949},{"id":99,"realGoldParam":4900,"realOfflineParam":4900,"showTips":300,"price":931067},{"id":100,"realGoldParam":4950,"realOfflineParam":4950,"showTips":303,"price":958999}]}