{"__type__":"cc.AnimationClip","_name":"ani-effect-rank-up","_duration":0.8333333333333334,"sample":30,"curveData":{"paths":{"effect-rank-01":{"props":{"opacity":[{"frame":0,"value":1},{"frame":0.3,"value":1},{"frame":0.36666666666666664,"value":255},{"frame":0.5666666666666667,"value":1}],"scale":[{"frame":0,"value":{"__type__":"cc.Vec2","x":1,"y":1}},{"frame":0.3,"value":{"__type__":"cc.Vec2","x":1,"y":1}},{"frame":0.5666666666666667,"value":{"__type__":"cc.Vec2","x":2.45,"y":1}}],"active":[{"frame":0,"value":true},{"frame":0.5666666666666667,"value":false}]}},"effect-rank-02":{"props":{"scale":[{"frame":0,"value":{"__type__":"cc.Vec2","x":1,"y":1}},{"frame":0.26666666666666666,"value":{"__type__":"cc.Vec2","x":1,"y":1}},{"frame":0.36666666666666664,"value":{"__type__":"cc.Vec2","x":2.86,"y":2.86},"curve":"cubicOut"},{"frame":0.5666666666666667,"value":{"__type__":"cc.Vec2","x":2.17,"y":2.17}}],"opacity":[{"frame":0,"value":1},{"frame":0.26666666666666666,"value":1},{"frame":0.36666666666666664,"value":255},{"frame":0.5666666666666667,"value":1}],"active":[{"frame":0,"value":true},{"frame":0.5666666666666667,"value":false}]}},"star02":{"props":{"scale":[{"frame":0,"value":{"__type__":"cc.Vec2","x":4.769999980926514,"y":4.769999980926514}},{"frame":0.26666666666666666,"value":{"__type__":"cc.Vec2","x":4.77,"y":4.77},"curve":"circIn"},{"frame":0.7333333333333333,"value":{"__type__":"cc.Vec2","x":1,"y":1}}],"opacity":[{"frame":0,"value":1},{"frame":0.36666666666666664,"value":1},{"frame":0.5333333333333333,"value":255},{"frame":0.8333333333333334,"value":1}],"color":[{"frame":0,"value":{"__type__":"cc.Color","r":255,"g":133,"b":25}},{"frame":0.36666666666666664,"value":{"__type__":"cc.Color","r":255,"g":133,"b":25}},{"frame":0.6333333333333333,"value":{"__type__":"cc.Color","r":255,"g":249,"b":122}},{"frame":0.8333333333333334,"value":{"__type__":"cc.Color","r":255,"g":255,"b":255}}],"active":[{"frame":0,"value":true},{"frame":0.8333333333333334,"value":false}]}},"star01":{"props":{"opacity":[{"frame":0,"value":1},{"frame":0.3333333333333333,"value":255},{"frame":0.6,"value":255},{"frame":0.7333333333333333,"value":1}],"active":[{"frame":0,"value":true},{"frame":0.7333333333333333,"value":false}]}}}}}